momotor/rpc/__init__.py
momotor/rpc/const.py
momotor/rpc/utils.py
momotor/rpc/asset/__init__.py
momotor/rpc/asset/exceptions.py
momotor/rpc/asset/remote.py
momotor/rpc/asset/server.py
momotor/rpc/asset/utils.py
momotor/rpc/auth/__init__.py
momotor/rpc/auth/client.py
momotor/rpc/auth/utils.py
momotor/rpc/exception/__init__.py
momotor/rpc/hash/__init__.py
momotor/rpc/hash/const.py
momotor/rpc/hash/funcs.py
momotor/rpc/hash/identity.py
momotor/rpc/proto/__init__.py
momotor/rpc/proto/asset.proto
momotor/rpc/proto/asset_grpc.py
momotor/rpc/proto/asset_pb2.py
momotor/rpc/proto/asset_pb2.pyi
momotor/rpc/proto/auth.proto
momotor/rpc/proto/auth_grpc.py
momotor/rpc/proto/auth_pb2.py
momotor/rpc/proto/auth_pb2.pyi
momotor/rpc/proto/client.proto
momotor/rpc/proto/client_grpc.py
momotor/rpc/proto/client_pb2.py
momotor/rpc/proto/client_pb2.pyi
momotor/rpc/proto/exception.proto
momotor/rpc/proto/exception_grpc.py
momotor/rpc/proto/exception_pb2.py
momotor/rpc/proto/exception_pb2.pyi
momotor/rpc/proto/grpc_proto.txt
momotor/rpc/proto/job.proto
momotor/rpc/proto/job_grpc.py
momotor/rpc/proto/job_pb2.py
momotor/rpc/proto/job_pb2.pyi
momotor/rpc/proto/priority.proto
momotor/rpc/proto/priority_grpc.py
momotor/rpc/proto/priority_pb2.py
momotor/rpc/proto/priority_pb2.pyi
momotor/rpc/proto/resource.proto
momotor/rpc/proto/resource_grpc.py
momotor/rpc/proto/resource_pb2.py
momotor/rpc/proto/resource_pb2.pyi
momotor/rpc/proto/shared.proto
momotor/rpc/proto/shared_grpc.py
momotor/rpc/proto/shared_pb2.py
momotor/rpc/proto/shared_pb2.pyi
momotor/rpc/proto/stats.proto
momotor/rpc/proto/stats_grpc.py
momotor/rpc/proto/stats_pb2.py
momotor/rpc/proto/stats_pb2.pyi
momotor/rpc/proto/task.proto
momotor/rpc/proto/task_grpc.py
momotor/rpc/proto/task_pb2.py
momotor/rpc/proto/task_pb2.pyi
momotor/rpc/proto/tool.proto
momotor/rpc/proto/tool_grpc.py
momotor/rpc/proto/tool_pb2.py
momotor/rpc/proto/tool_pb2.pyi
momotor/rpc/proto/worker.proto
momotor/rpc/proto/worker_grpc.py
momotor/rpc/proto/worker_pb2.py
momotor_engine_proto-5.1.0.dist-info/METADATA
momotor_engine_proto-5.1.0.dist-info/WHEEL
momotor_engine_proto-5.1.0.dist-info/top_level.txt
momotor_engine_proto-5.1.0.dist-info/RECORD
